plotnine_examples/__init__.py
plotnine_examples/notebooks/__init__.py
plotnine_examples/notebooks/geom_col.ipynb
plotnine_examples/notebooks/geom_point.ipynb
plotnine_examples/notebooks/geom_tile.ipynb
plotnine_examples/notebooks/theme.ipynb
plotnine_examples/notebooks/data/elements.csv
plotnine_examples-0.0.4.dist-info/DESCRIPTION.rst
plotnine_examples-0.0.4.dist-info/METADATA
plotnine_examples-0.0.4.dist-info/RECORD
plotnine_examples-0.0.4.dist-info/WHEEL
plotnine_examples-0.0.4.dist-info/metadata.json
plotnine_examples-0.0.4.dist-info/top_level.txt
