Metadata-Version: 2.0
Name: plotnine-examples
Version: 0.0.4
Summary: Usage examples for plotnine
Home-page: https://github.com/has2k1/plotnine-examples
Author: Hassan Kibirige
Author-email: has2k1@gmail.com
License: BSD (3-clause)
Platform: UNKNOWN
Classifier: Intended Audience :: Science/Research
Classifier: License :: OSI Approved :: BSD License
Classifier: Operating System :: Microsoft :: Windows
Classifier: Operating System :: Unix
Classifier: Operating System :: MacOS
Classifier: Programming Language :: Python :: 2
Classifier: Programming Language :: Python :: 3
